LICENSE
README
setup.py
easilyb/__init__.py
easilyb/cache.py
easilyb/config.py
easilyb/crypto.py
easilyb/docker.py
easilyb/flaskutils.py
easilyb/json_ipc.py
easilyb/json_serialize.py
easilyb/lockfile.py
easilyb/logs.py
easilyb/queueworker.py
easilyb/terminal.py
easilyb/urlnorm.py
easilyb.egg-info/PKG-INFO
easilyb.egg-info/SOURCES.txt
easilyb.egg-info/dependency_links.txt
easilyb.egg-info/requires.txt
easilyb.egg-info/top_level.txt
easilyb/commands/__init__.py
easilyb/commands/_commands.py
easilyb/commands/imagemagick.py
easilyb/commands/os_ops.py
easilyb/commands/rsync.py
easilyb/crawler/__init__.py
easilyb/databases/__init__.py
easilyb/databases/elasticsearch.py
easilyb/databases/mongo.py
easilyb/file_ops/__init__.py
easilyb/file_ops/_file_ops.py
easilyb/json_min_db/__init__.py
easilyb/net/__init__.py
easilyb/net/ip.py
easilyb/net/requestqueue.py
easilyb/net/whois.py
easilyb/os_ops/__init__.py
easilyb/os_ops/desktop.py
easilyb/os_ops/linux/__init__.py
easilyb/os_ops/linux/ps.py
easilyb/os_ops/linux/xdotool.py
easilyb/os_ops/linux/xprop.py
easilyb/serialization/__init__.py
easilyb/serialization/map.py
easilyb/socket_ops/__init__.py
easilyb/string_ops/__init__.py
easilyb/string_ops/_string_ops.py
easilyb/threads/__init__.py
easilyb/time_ops/__init__.py
easilyb/time_ops/_time_ops.py
easilyb/urlselector/__init__.py
easilyb/urlselector/ratequeue.py
easilyb/validators/__init__.py
easilyb/validators/ip.py